music_scripts/__init__.py
music_scripts/__main__.py
music_scripts/config.py
music_scripts/constants.py
music_scripts/derived_fields.py
music_scripts/eos.py
music_scripts/fgong.py
music_scripts/field.py
music_scripts/figure.py
music_scripts/fort_pp.py
music_scripts/globdiag.py
music_scripts/igw.py
music_scripts/info.py
music_scripts/lmax.py
music_scripts/lyon1d.py
music_scripts/make_movie.py
music_scripts/musicdata.py
music_scripts/pert_plot.py
music_scripts/plot_pendepth.py
music_scripts/plots.py
music_scripts/plots_old.py
music_scripts/py.typed
music_scripts/renumber.py
music_scripts/restart.py
music_scripts/river.py
music_scripts/rprof.py
music_scripts/to_vtk.py
music_scripts/tseries.py
music_scripts-0.1.0.dist-info/METADATA
music_scripts-0.1.0.dist-info/WHEEL
music_scripts-0.1.0.dist-info/entry_points.txt
music_scripts-0.1.0.dist-info/licenses/LICENSE
music_scripts-0.1.0.dist-info/RECORD
