Metadata-Version: 2.3
Name: music_scripts
Version: 0.1.0
Summary: MUSIC toolshed
Project-URL: homepage, https://github.com/amorison/music_scripts/
Author-email: Adrien Morison <adrien.morison@gmail.com>
License: MIT License
License-File: LICENSE
Classifier: Development Status :: 3 - Alpha
Classifier: Intended Audience :: Science/Research
Classifier: License :: OSI Approved :: MIT License
Classifier: Programming Language :: Python :: 3 :: Only
Classifier: Programming Language :: Python :: 3.10
Classifier: Programming Language :: Python :: 3.11
Classifier: Programming Language :: Python :: 3.12
Classifier: Programming Language :: Python :: 3.13
Requires-Python: >=3.10
Requires-Dist: f90nml>=1.4.4
Requires-Dist: h5py>=3.12
Requires-Dist: loam<0.9.0,>=0.8.0
Requires-Dist: matplotlib>=3.9
Requires-Dist: music-mesa-tables~=0.2.2
Requires-Dist: music-pykg~=7.1
Requires-Dist: numpy>=2.1
Requires-Dist: pyevtk>=1.6
Requires-Dist: pymusic-astro~=3.0
Requires-Dist: scipy>=1.14
Requires-Dist: tomso>=0.2.1
